pyioga/__init__.py
pyioga/__main__.py
pyioga-0.1.0.dist-info/LICENSE
pyioga-0.1.0.dist-info/METADATA
pyioga-0.1.0.dist-info/WHEEL
pyioga-0.1.0.dist-info/entry_points.txt
pyioga-0.1.0.dist-info/top_level.txt
pyioga-0.1.0.dist-info/RECORD
