Metadata-Version: 2.1
Name: pyioga
Version: 0.1.0
Summary: Python IMAP OAuth2 Google Authenticator
Home-page: https://github.com/mbroton/pyioga
Author: Michal Broton
Author-email: michal@broton.dev
License: GPL-3.0
Platform: UNKNOWN
Classifier: Intended Audience :: Developers
Classifier: License :: OSI Approved :: GNU General Public License v3 (GPLv3)
Classifier: Operating System :: POSIX :: Linux
Classifier: Programming Language :: Python :: 3
Classifier: Topic :: Communications :: Email :: Post-Office :: IMAP
Requires-Dist: click (>=8.1.3)
Requires-Dist: google-api-python-client (>=2.49.0)
Requires-Dist: google-auth-httplib2 (>=0.1.0)
Requires-Dist: google-auth-oauthlib (>=0.5.1)
Requires-Dist: google-auth (>=2.6.6)
